aprofs/__init__.py
aprofs/code.py
aprofs/models.py
aprofs/utils.py
aprofs-0.0.5.dist-info/METADATA
aprofs-0.0.5.dist-info/WHEEL
aprofs-0.0.5.dist-info/RECORD
