Metadata-Version: 2.1
Name: aprofs
Version: 0.0.5
Summary: "Package aprofs serves the purpose of streaming the feature selection using aproximate preditions"
License: MIT
Keywords: one,two
Author: Filipe Santos
Requires-Python: >=3.9,<4.0
Classifier: License :: OSI Approved :: MIT License
Classifier: Programming Language :: Python :: 3
Classifier: Programming Language :: Python :: 3.9
Classifier: Programming Language :: Python :: 3.10
Classifier: Programming Language :: Python :: 3.11
Classifier: Programming Language :: Python :: 3.12
Requires-Dist: lightgbm (>=4.3.0,<5.0.0)
Requires-Dist: nbformat (>=5.10.4,<6.0.0)
Requires-Dist: pandas (>=2.2.1,<3.0.0)
Requires-Dist: plotly (>=5.20.0,<6.0.0)
Requires-Dist: polars (>=0.20.18,<0.21.0)
Requires-Dist: scikit-learn (>=1.4.1.post1,<2.0.0)
Requires-Dist: seaborn (>=0.13.2,<0.14.0)
Requires-Dist: shap (>=0.45.0,<0.46.0)
Requires-Dist: tqdm (>=4.66.2,<5.0.0)
